ORBIS_new/__init__.py
ORBIS_new/ace/__init__.py
ORBIS_new/ace/config.py
ORBIS_new/ace/load.py
ORBIS_new/ae/__init__.py
ORBIS_new/ae/config.py
ORBIS_new/ae/load.py
ORBIS_new/dst/__init__.py
ORBIS_new/dst/config.py
ORBIS_new/dst/load.py
ORBIS_new/dst_kyoto/__init__.py
ORBIS_new/dst_kyoto/config.py
ORBIS_new/dst_kyoto/load.py
ORBIS_new/model/__init__.py
ORBIS_new/predict/__init__.py
ORBIS_new/predict/config.py
ORBIS_new/predict/predict.py
ORBIS_new/predict/realtime_read.py
orbis_new-0.1.1.dist-info/LICENSE
orbis_new-0.1.1.dist-info/METADATA
orbis_new-0.1.1.dist-info/WHEEL
orbis_new-0.1.1.dist-info/top_level.txt
orbis_new-0.1.1.dist-info/RECORD
