Metadata-Version: 2.1
Name: orbis-new
Version: 0.1.1
Summary: Real time Electron flux data
Home-page: https://github.com/donglai96/ORBIS_new
Author: Donglai Ma
Author-email: dma96@atmos.ucla.edu
License: MIT
Keywords: predict radiation-belt
Platform: UNKNOWN
Classifier: Development Status :: 4 - Beta
Classifier: Intended Audience :: Science/Research
Classifier: Topic :: Scientific/Engineering
Classifier: License :: OSI Approved :: MIT License
Classifier: Programming Language :: Python :: 3.7
Requires-Python: >=3.5
Requires-Dist: numpy
Requires-Dist: mechanize
Requires-Dist: tensorflow (>=2.0)
Requires-Dist: scipy
Requires-Dist: pandas
Requires-Dist: matplotlib
